<dungeon>

  <tile>
    <symbol>@</symbol>
    <isobject>PlayerStart</isobject>
  </tile>
  <tile>
    <symbol>t</symbol>
    <isobject>Torch</isobject>
  </tile>
  <tile>
    <symbol>b</symbol>
    <isobject>MurderBirb</isobject>
  </tile>
  <tile>
    <symbol>#</symbol>
    <isobject>BrickBlock</isobject>
  </tile>
  <tile>
    <symbol>X</symbol>
    <isobject>BrickBlockDark</isobject>
  </tile>
  
  <screen id="screen0">
    <grid zpos="0">
      ##########
      #........#
      #........#
      #........#
      #........#
      #t......t#
      ##......##
      #........#
      #.@...b..#
      ##########
    </grid>
    <grid zpos="2">
      XXXXXXXXXX
      XXXXXXXXXX
      XXXXXXXXXX
      XXXXXXXXXX
      XXX.XX.XXX
      XXX.XX.XXX
      XXXXXXXXXX
      XXXXXXXXXX
      XXXXXXXXXX
      XXXXXXXXXX
    </grid>
    <grid zpos="1">
      XXXXXXXXXX
      XXXXXXXXXX
      XX......XX
      XX......XX
      XX......XX
      XX......XX
      XX......XX
      XX......XX
      XXXXXXXXXX
      XXXXXXXXXX
    </grid>
  </screen>
  
</dungeon>
